MANIFEST.in
readme.rst
setup.py
CarryLessRangeCoder.egg-info/PKG-INFO
CarryLessRangeCoder.egg-info/SOURCES.txt
CarryLessRangeCoder.egg-info/dependency_links.txt
CarryLessRangeCoder.egg-info/top_level.txt
carryless_rangecoder/__init__.py
carryless_rangecoder/codec.py