Metadata-Version: 1.0
Name: CarryLessRangeCoder
Version: 1.0.2
Summary: Python implementation of carry-less range coder
Home-page: https://github.com/hiroki-kojima/CarryLessRangeCoder
Author: hiroki-kojima
Author-email: hiroki.kojima.1997@gmail.com
License: UNKNOWN
Platform: UNKNOWN
